{"org":"ballerinax", "name":"hubspot.crm.import", "version":"1.0.0", "platform":"any", "ballerina_version":"2201.10.0", "is_deprecated":false, "deprecation_message":"", "modules":[{"name":"hubspot.crm.import"}], "dependencies":[{"org":"ballerina", "name":"url", "version":"2.4.0"}, {"org":"ballerina", "name":"os", "version":"1.8.0"}, {"org":"ballerina", "name":"io", "version":"1.6.1"}, {"org":"ballerina", "name":"oauth2", "version":"2.12.0"}, {"org":"ballerina", "name":"mime", "version":"2.10.1"}, {"org":"ballerina", "name":"http", "version":"2.12.4"}]}
{"org":"ballerinax", "name":"hubspot.crm.import", "version":"1.1.0", "platform":"any", "ballerina_version":"slbeta6", "is_deprecated":false, "deprecation_message":"", "modules":[{"name":"hubspot.crm.import"}], "dependencies":[{"org":"ballerina", "name":"url", "version":"2.1.0"}, {"org":"ballerina", "name":"mime", "version":"2.1.0"}, {"org":"ballerina", "name":"http", "version":"2.1.0"}]}
{"org":"ballerinax", "name":"hubspot.crm.import", "version":"1.2.0", "platform":"any", "ballerina_version":"2201.0.0", "is_deprecated":false, "deprecation_message":"", "modules":[{"name":"hubspot.crm.import"}], "dependencies":[{"org":"ballerina", "name":"url", "version":"2.2.0"}, {"org":"ballerina", "name":"mime", "version":"2.2.0"}, {"org":"ballerina", "name":"http", "version":"2.2.0"}]}
{"org":"ballerinax", "name":"hubspot.crm.import", "version":"2.0.0", "platform":"any", "ballerina_version":"2201.0.2", "is_deprecated":false, "deprecation_message":"", "modules":[{"name":"hubspot.crm.import"}], "dependencies":[{"org":"ballerina", "name":"url", "version":"2.2.1"}, {"org":"ballerina", "name":"mime", "version":"2.2.1"}, {"org":"ballerina", "name":"http", "version":"2.2.1"}]}
